gravithon/Body.py
gravithon/Circle.py
gravithon/Line.py
gravithon/Screen.py
gravithon/Space.py
gravithon/Sphere.py
gravithon/__init__.py
gravithon/errors.py
gravithon/formulas.py
gravithon/astronomy/Planet.py
gravithon/astronomy/Planets.py
gravithon/astronomy/Satellite.py
gravithon/constants/astrophisics.py
gravithon/fields/Field.py
gravithon/fields/GravitationalField.py
gravithon/units/length.py
gravithon/units/mass.py
gravithon/units/prefixes.py
gravithon/units/time.py
gravithon-0.0.20.dist-info/LICENSE
gravithon-0.0.20.dist-info/METADATA
gravithon-0.0.20.dist-info/WHEEL
gravithon-0.0.20.dist-info/top_level.txt
gravithon-0.0.20.dist-info/RECORD
