Metadata-Version: 2.1
Name: gravithon
Version: 0.0.20
Summary: Create multy-dimensional python spaces
Author-email: Yehuda Elyasaf <30yehuda26@gmail.com>
Maintainer-email: Yehuda Elyasaf <30yehuda26@gmail.com>
Project-URL: Homepage, https://github.com/YehudaElyasaf/gravithon
Project-URL: Issues, https://github.com/YehudaElyasaf/gravithon/issues
Keywords: physics,2d,3d,engine
Classifier: License :: OSI Approved :: MIT License
Classifier: Operating System :: OS Independent
License-File: LICENSE
Requires-Dist: numpy
Requires-Dist: multipledispatch
Requires-Dist: Pillow
Requires-Dist: datetime
